sagemill/__init__.py
sagemill/builder.py
sagemill/converter.py
sagemill/process.py
sagemill/train.py
sagemill/docker/process/Dockerfile
sagemill/docker/train/Dockerfile
sagemill/docker/train/entrypoint.sh
sagemill-0.0.1.dist-info/METADATA
sagemill-0.0.1.dist-info/WHEEL
sagemill-0.0.1.dist-info/top_level.txt
sagemill-0.0.1.dist-info/RECORD
