Metadata-Version: 2.1
Name: sagemill
Version: 0.0.1
Summary: Run SageMaker Job like Papermil
Home-page: https://github.com/yuki-mt/sagemill/
Author: yuki-mt
Author-email: yuki-mt@gmail.com
License: Apache License 2.0
Keywords: sagemaker,papermill
Platform: UNKNOWN
Classifier: License :: OSI Approved :: Apache Software License
Classifier: Programming Language :: Python :: 3
Classifier: Programming Language :: Python :: 3.5
Classifier: Programming Language :: Python :: 3.6
Classifier: Topic :: Software Development :: Libraries :: Python Modules
Requires-Dist: jupyter (>=1.0)
Requires-Dist: boto3 (>=1.12)
Requires-Dist: docker (>=4.2)
Requires-Dist: pipreqs (>=0.4)
